Terminal_Speil_Main.py
game_data.py
save_system.py
utils.py
Terminal_Speil_B1-1.1.2.dist-info/METADATA
Terminal_Speil_B1-1.1.2.dist-info/WHEEL
Terminal_Speil_B1-1.1.2.dist-info/entry_points.txt
Terminal_Speil_B1-1.1.2.dist-info/top_level.txt
Terminal_Speil_B1-1.1.2.dist-info/RECORD
