Metadata-Version: 2.1
Name: Terminal-Speil-B1
Version: 1.1.2
Summary: A terminal-based spelling game
Home-page: https://github.com/basanta-bhandari/Summer_of_Making
Author: Basanta Bhandari
Author-email: bhandari.basanta.47@gmail.com
Classifier: Development Status :: 4 - Beta
Classifier: Intended Audience :: End Users/Desktop
Classifier: Programming Language :: Python :: 3
Classifier: Programming Language :: Python :: 3.7
Classifier: Programming Language :: Python :: 3.8
Classifier: Programming Language :: Python :: 3.9
Classifier: Programming Language :: Python :: 3.10
Classifier: Programming Language :: Python :: 3.11
Classifier: Topic :: Games/Entertainment :: Role-Playing
Requires-Python: >=3.7
